volder/__init__.py
volder/config_parameters.ini
volder/py.typed
volder/volder.py
volder-0.0.2.dist-info/LICENSE
volder-0.0.2.dist-info/METADATA
volder-0.0.2.dist-info/WHEEL
volder-0.0.2.dist-info/entry_points.txt
volder-0.0.2.dist-info/top_level.txt
volder-0.0.2.dist-info/RECORD
