Metadata-Version: 2.1
Name: volder
Version: 0.0.2
Summary: Conversão de volume derivados
Home-page: https://github.com/adrianosturaro/volconv.git
Author: Adriano Fernando Sturaro
Author-email: adrianosturaro@yahoo.com.br
License: MIT
Platform: unix
Platform: linux
Platform: osx
Platform: cygwin
Platform: win32
Classifier: License :: OSI Approved :: MIT License
Classifier: Programming Language :: Python :: 3
Classifier: Programming Language :: Python :: 3 :: Only
Classifier: Programming Language :: Python :: 3.6
Classifier: Programming Language :: Python :: 3.7
Classifier: Operating System :: OS Independent
Requires-Python: >=3.6
License-File: LICENSE
Requires-Dist: pydantic
Requires-Dist: numpy
Provides-Extra: dev
Requires-Dist: pytest (==7.1.2) ; extra == 'dev'
Requires-Dist: flake8 (==4.0.1) ; extra == 'dev'
Requires-Dist: mypy (==0.960) ; extra == 'dev'
Requires-Dist: black (==22.3.0) ; extra == 'dev'
